{
	"name": "XLS_SUPER_STORE_SALES_DATA_PEOPLE",
	"properties": {
		"linkedServiceName": {
			"referenceName": "AzureBlobStoragegr3",
			"type": "LinkedServiceReference"
		},
		"annotations": [],
		"type": "Excel",
		"typeProperties": {
			"sheetName": "People",
			"location": {
				"type": "AzureBlobStorageLocation",
				"fileName": "Superstore Sales Data.xlsx",
				"folderPath": "FISICA",
				"container": "contenedor-gr3"
			},
			"firstRowAsHeader": true
		},
		"schema": [
			{
				"name": "Person",
				"type": "String"
			},
			{
				"name": "Region",
				"type": "String"
			}
		]
	}
}